AUTHORS
ChangeLog
LICENSE
README.md
requirements.txt
setup.cfg
setup.py
test_requirements.txt
tox.ini
notification_utils/__init__.py
notification_utils.egg-info/PKG-INFO
notification_utils.egg-info/SOURCES.txt
notification_utils.egg-info/dependency_links.txt
notification_utils.egg-info/not-zip-safe
notification_utils.egg-info/pbr.json
notification_utils.egg-info/requires.txt
notification_utils.egg-info/top_level.txt
tests/test_utils.py